odoo/addons/l10n_ir_accounting/README.rst
odoo/addons/l10n_ir_accounting/__init__.py
odoo/addons/l10n_ir_accounting/__manifest__.py
odoo/addons/l10n_ir_accounting/data/account.account.template.csv
odoo/addons/l10n_ir_accounting/data/account.group.template.csv
odoo/addons/l10n_ir_accounting/data/account_chart_template_data.xml
odoo/addons/l10n_ir_accounting/data/account_fiscal_position_data.xml
odoo/addons/l10n_ir_accounting/data/account_tax_group_data.xml
odoo/addons/l10n_ir_accounting/data/account_tax_template_data.xml
odoo/addons/l10n_ir_accounting/data/l10n_ir_chart_data.xml
odoo/addons/l10n_ir_accounting/data/l10n_ir_chart_post_data.xml
odoo/addons/l10n_ir_accounting/data/res.bank.csv
odoo/addons/l10n_ir_accounting/data/res_currency_data.xml
odoo/addons/l10n_ir_accounting/i18n/fa.po
odoo/addons/l10n_ir_accounting/i18n/l10n_ir_accounting.pot
odoo/addons/l10n_ir_accounting/static/description/icon.png
odoo_addon_l10n_ir_accounting-16.0.1.0.1.dist-info/METADATA
odoo_addon_l10n_ir_accounting-16.0.1.0.1.dist-info/WHEEL
odoo_addon_l10n_ir_accounting-16.0.1.0.1.dist-info/top_level.txt
odoo_addon_l10n_ir_accounting-16.0.1.0.1.dist-info/RECORD
